citus_rebalancer/__init__.py
citus_rebalancer/base.py
citus_rebalancer/classes.py
citus_rebalancer/command.py
py_citus_rebalancer-1.0.4.dist-info/LICENSE
py_citus_rebalancer-1.0.4.dist-info/METADATA
py_citus_rebalancer-1.0.4.dist-info/WHEEL
py_citus_rebalancer-1.0.4.dist-info/entry_points.txt
py_citus_rebalancer-1.0.4.dist-info/top_level.txt
py_citus_rebalancer-1.0.4.dist-info/RECORD
